Metadata-Version: 2.4
Name: onvif-zeep-async
Version: 4.0.4
Summary: Async Python Client for ONVIF Camera
Home-page: http://github.com/hunterjm/python-onvif-zeep-async
Author: Cherish Chen
Author-email: sinchb128@gmail.com
Maintainer: sinchb
Maintainer-email: sinchb128@gmail.com
License: MIT
Keywords: ONVIF,Camera,IPC
Requires-Python: >=3.10
License-File: LICENSE
Requires-Dist: aiohttp>=3.12.9
Requires-Dist: httpx<1.0.0,>=0.19.0
Requires-Dist: zeep[async]<5.0.0,>=4.2.1
Requires-Dist: ciso8601>=2.1.3
Requires-Dist: yarl>=1.10.0
Dynamic: author
Dynamic: author-email
Dynamic: description
Dynamic: home-page
Dynamic: keywords
Dynamic: license
Dynamic: license-file
Dynamic: maintainer
Dynamic: maintainer-email
Dynamic: requires-dist
Dynamic: requires-python
Dynamic: summary
